AIUT_RoboticsToolbox/Toolbox.py
AIUT_RoboticsToolbox/__init__.py
aiut_roboticstoolbox-0.0.0.6.dist-info/METADATA
aiut_roboticstoolbox-0.0.0.6.dist-info/WHEEL
aiut_roboticstoolbox-0.0.0.6.dist-info/top_level.txt
aiut_roboticstoolbox-0.0.0.6.dist-info/RECORD
