Metadata-Version: 2.2
Name: AIUT_RoboticsToolbox
Version: 0.0.0.6
Summary: A simple Robotics package
Home-page: https://github.com/pypa/AIUT_RoboticsToolBox
Author: Maziar Palhang
Author-email: Maziar Palhang <palhang@iut.ac.ir>
Project-URL: Homepage, https://github.com/pypa/AIUT_RoboticsToolbox
Project-URL: Issues, https://github.com/pypa/AIUT_RoboticsToolbox/issues
Classifier: Programming Language :: Python :: 3
Classifier: Operating System :: OS Independent
Classifier: License :: OSI Approved :: MIT License
Requires-Python: >=3.8
